mciutil/_version.py
mciutil/__init__.py
mciutil/mciutil.py
mciutil/cli/mideu.yml
mciutil/cli/convert.py
mciutil/cli/__init__.py
mciutil/cli/mideu.py
mciutil/cli/common.py
mciutil/cli/paramconv.py
mciutil/cli/extract.py
mciutil-0.7.1.dist-info/RECORD
mciutil-0.7.1.dist-info/metadata.json
mciutil-0.7.1.dist-info/WHEEL
mciutil-0.7.1.dist-info/entry_points.txt
mciutil-0.7.1.dist-info/DESCRIPTION.rst
mciutil-0.7.1.dist-info/top_level.txt
mciutil-0.7.1.dist-info/METADATA
