Metadata-Version: 2.0
Name: mciutil
Version: 0.7.1
Summary: MasterCard file utilities
Home-page: https://github.com/adelosa/mciutil
Author: Anthony Delosa
Author-email: adelosa@gmail.com
License: BSD
Keywords: mciutil
Platform: UNKNOWN
Classifier: Development Status :: 2 - Pre-Alpha
Classifier: Intended Audience :: Developers
Classifier: License :: OSI Approved :: BSD License
Classifier: Natural Language :: English
Classifier: Programming Language :: Python :: 2
Classifier: Programming Language :: Python :: 2.7
Classifier: Programming Language :: Python :: 3
Classifier: Programming Language :: Python :: 3.5
Classifier: Programming Language :: Python :: 3.6
Classifier: Programming Language :: Python :: 3.7
Requires-Dist: PyYAML
Requires-Dist: hexdump
Requires-Dist: argparse
